deepread/__init__.py
deepread/config.py
deepread/exceptions.py
deepread/ocr.py
deepread/reader.py
deepread/utils.py
deepread/auth/__init__.py
deepread/auth/exceptions.py
deepread/auth/token.py
deepread/models/__init__.py
deepread/models/classification.py
deepread/models/question.py
deepread/models/result.py
deepread/models/schemas.py
deepread_monkai-2.0.9.dist-info/METADATA
deepread_monkai-2.0.9.dist-info/WHEEL
deepread_monkai-2.0.9.dist-info/top_level.txt
deepread_monkai-2.0.9.dist-info/RECORD
