Metadata-Version: 2.4
Name: DeepRead.Monkai
Version: 2.0.9
Summary: Biblioteca para extração inteligente de documentos PDF com IA
Author-email: Monkai <contato@monkai.com.br>
License: MIT
Project-URL: Homepage, https://github.com/BeMonkAI/deepread
Project-URL: Documentation, https://github.com/BeMonkAI/deepread#readme
Project-URL: Repository, https://github.com/BeMonkAI/deepread
Project-URL: Issues, https://github.com/BeMonkAI/deepread/issues
Keywords: pdf,extraction,ai,ocr,document,llm,openai
Classifier: Development Status :: 4 - Beta
Classifier: Intended Audience :: Developers
Classifier: License :: OSI Approved :: MIT License
Classifier: Programming Language :: Python :: 3
Classifier: Programming Language :: Python :: 3.9
Classifier: Programming Language :: Python :: 3.10
Classifier: Programming Language :: Python :: 3.11
Classifier: Programming Language :: Python :: 3.12
Classifier: Topic :: Scientific/Engineering :: Artificial Intelligence
Classifier: Topic :: Text Processing :: General
Requires-Python: >=3.9
Requires-Dist: pydantic>=2.0.0
Requires-Dist: python-dotenv>=1.0.0
Requires-Dist: openai>=1.0.0
Requires-Dist: tiktoken>=0.5.0
Requires-Dist: llama-index-readers-file>=0.1.0
Requires-Dist: llama-index-core>=0.10.0
Requires-Dist: pypdf>=4.0.0
Requires-Dist: PyMuPDF>=1.24.0
Requires-Dist: requests>=2.28.0
Provides-Extra: ocr
Requires-Dist: azure-ai-vision-imageanalysis>=1.0.0; extra == "ocr"
Requires-Dist: Pillow>=10.0.0; extra == "ocr"
Provides-Extra: dev
Requires-Dist: pytest>=7.0.0; extra == "dev"
Requires-Dist: pytest-cov>=4.0.0; extra == "dev"
Requires-Dist: black>=23.0.0; extra == "dev"
Requires-Dist: ruff>=0.1.0; extra == "dev"
Provides-Extra: all
Requires-Dist: deepread[dev,ocr]; extra == "all"
